Hanguel/__init__.py
Hanguel/alphabets.py
Hanguel/compose.py
Hanguel/decompose.py
Hanguel/utils.py
Hanguel-0.0.0.6.dist-info/LICENSE.txt
Hanguel-0.0.0.6.dist-info/METADATA
Hanguel-0.0.0.6.dist-info/WHEEL
Hanguel-0.0.0.6.dist-info/top_level.txt
Hanguel-0.0.0.6.dist-info/RECORD
