Metadata-Version: 2.1
Name: Hanguel
Version: 0.0.0.6
Summary: Python Hanguel preprocess package for TTS(Text To Speech) STT | TTB(Text To Braille) BTT |
Home-page: https://github.com/indiaprince/Hanguel
Author: indiaprince
Author-email: hyeonsuhan@gmail.com
License: MIT
Keywords: Python Project For Hanguel Decomposition & Construction
Platform: UNKNOWN
Classifier: Programming Language :: Python :: 3
Classifier: License :: OSI Approved :: MIT License
Classifier: Operating System :: OS Independent
Requires-Python: >=3.6
